charSn/__init__.py
charSn/ch.py
charsn-0.0.7.dist-info/METADATA
charsn-0.0.7.dist-info/WHEEL
charsn-0.0.7.dist-info/licenses/LICENSE
charsn-0.0.7.dist-info/RECORD
